compatibilityer/__init__.py
compatibilityer/convert.py
compatibilityer/converter.py
compatibilityer/main.py
compatibilityer/version.py
compatibilityer-0.3.8.dist-info/LICENSE
compatibilityer-0.3.8.dist-info/WHEEL
compatibilityer-0.3.8.dist-info/METADATA
compatibilityer-0.3.8.dist-info/RECORD
