Metadata-Version: 2.1
Name: compatibilityer
Version: 0.3.8
Summary: Tool to convert Python code to work with older versions
License: MIT
Author: nahco314
Author-email: nahco3_ta@yahoo.co.jp
Requires-Python: >=3.10,<4.0
Classifier: License :: OSI Approved :: MIT License
Classifier: Programming Language :: Python :: 3
Classifier: Programming Language :: Python :: 3.10
Classifier: Programming Language :: Python :: 3.11
